lcdk/__init__.py
lcdk/lcdk.py
lcdk-0.3.dist-info/LICENSE
lcdk-0.3.dist-info/METADATA
lcdk-0.3.dist-info/WHEEL
lcdk-0.3.dist-info/top_level.txt
lcdk-0.3.dist-info/RECORD
