Metadata-Version: 2.1
Name: lcdk
Version: 0.3
Summary: Leslie Chow Debug Kit
Home-page: https://github.com/senorChow/lcdk.git
Author: John M. Cook
Author-email: jmcook1982@protonmail.com
License: MIT
Platform: UNKNOWN
Classifier: Programming Language :: Python :: 3
Classifier: License :: OSI Approved :: MIT License
Classifier: Operating System :: OS Independent
